KruskalHamiltonPrimal/Hamiltonian_cycle.py
KruskalHamiltonPrimal/Kruskals_algorithm.py
KruskalHamiltonPrimal/Primal.py
KruskalHamiltonPrimal/__init__.py
KruskalHamiltonPrimal-0.1.2.dist-info/METADATA
KruskalHamiltonPrimal-0.1.2.dist-info/WHEEL
KruskalHamiltonPrimal-0.1.2.dist-info/top_level.txt
KruskalHamiltonPrimal-0.1.2.dist-info/RECORD
