Metadata-Version: 2.1
Name: KruskalHamiltonPrimal
Version: 0.1.2
Summary: Библиотека для работы с графами и алгоритмами, включая алгоритмы Крускала, Гамильтона и минимального остовного дерева
Home-page: https://github.com/Ksenia72/graph_algorithms
Author: Prosina_Chetvergova_Toychubecova
Author-email: prosinaksenia@gmail.com
Project-URL: GitHub, https://github.com/Ksenia72
Keywords: графы алгоритмы Крускала Краскала Гамильтона минимальное остовное дерево
Classifier: Programming Language :: Python :: 3.11
Classifier: License :: OSI Approved :: MIT License
Classifier: Operating System :: OS Independent
Requires-Python: >=3.6
Requires-Dist: matplotlib
Requires-Dist: networkx
